CHIMERA/__init__.py
CHIMERA/catalog/__init__.py
CHIMERA/catalog/catalog.py
CHIMERA/catalog/completeness.py
CHIMERA/data.py
CHIMERA/likelihood.py
CHIMERA/parallel.py
CHIMERA/population/__init__.py
CHIMERA/population/cosmo.py
CHIMERA/population/mass.py
CHIMERA/population/pop_wrapper.py
CHIMERA/population/rate.py
CHIMERA/selection_function.py
CHIMERA/utils/angles.py
CHIMERA/utils/config.py
CHIMERA/utils/emcee_utils.py
CHIMERA/utils/io.py
CHIMERA/utils/mags.py
CHIMERA/utils/math.py
CHIMERA/utils/plotting.py
chimera_gw-2.0.0.dist-info/LICENSE
chimera_gw-2.0.0.dist-info/METADATA
chimera_gw-2.0.0.dist-info/WHEEL
chimera_gw-2.0.0.dist-info/RECORD
