Metadata-Version: 2.1
Name: chimera-gw
Version: 2.0.0
Summary: Combined Hierarchical Inference Model for Electromagnetic and gRavitational-wave Analysis
Home-page: https://github.com/CosmoStatGW/CHIMERA
License: GPL-3.0-or-later
Author: Nicola Borghi
Author-email: nicola.borghi6@unibo.it
Requires-Python: >=3.10
Classifier: License :: OSI Approved :: GNU General Public License v3 or later (GPLv3+)
Classifier: Programming Language :: Python :: 3
Classifier: Programming Language :: Python :: 3.10
Classifier: Programming Language :: Python :: 3.11
Classifier: Programming Language :: Python :: 3.12
Provides-Extra: all
Provides-Extra: docs
Provides-Extra: mpi
Provides-Extra: plots
Requires-Dist: astropy (>=5.2)
Requires-Dist: cython
Requires-Dist: emcee
Requires-Dist: equinox
Requires-Dist: h5py (>=3.5)
Requires-Dist: healpy (>=1.14)
Requires-Dist: interpax
Requires-Dist: jax (>=0.5)
Requires-Dist: matplotlib (>=3.4) ; extra == "plots" or extra == "docs" or extra == "all"
Requires-Dist: mpi4jax[no-build-isolation] ; extra == "mpi" or extra == "all"
Requires-Dist: mpi4py (>=4.0) ; extra == "mpi" or extra == "all"
Requires-Dist: myst-nb (>=0.17.0) ; extra == "docs"
Requires-Dist: myst-parser (>=0.18.1) ; extra == "docs"
Requires-Dist: nbsphinx (>=0.8.10) ; extra == "docs"
Requires-Dist: numba (>=0.58)
Requires-Dist: numpy (>=2.0)
Requires-Dist: packaging
Requires-Dist: plum-dispatch
Requires-Dist: requests (>=2.31.0)
Requires-Dist: schwimmbad (>=0.3.2) ; extra == "mpi" or extra == "all"
Requires-Dist: scikit-learn (>=1.0)
Requires-Dist: scipy (>=1.11)
Requires-Dist: setuptools
Requires-Dist: sphinx (>=5.3.0) ; extra == "docs"
Requires-Dist: sphinx-book-theme (>=1.0) ; extra == "docs"
Requires-Dist: sphinx-copybutton (>=0.5.1) ; extra == "docs"
Requires-Dist: wheel
Project-URL: Documentation, https://chimera-gw.readthedocs.io/latest/
Project-URL: Repository, https://github.com/CosmoStatGW/CHIMERA
